jppy/__init__.py
jppy/pdf.cpython-37m-darwin.so
jppy/version.py
jppy-3.2.2.dist-info/LICENSE
jppy-3.2.2.dist-info/METADATA
jppy-3.2.2.dist-info/WHEEL
jppy-3.2.2.dist-info/top_level.txt
jppy-3.2.2.dist-info/RECORD
