Metadata-Version: 2.1
Name: jppy
Version: 3.2.2
Summary: Jpp Python Package
Home-page: https://git.km3net.de/km3py/jppy
Author: Tamas Gal
Author-email: tgal@km3net.de
License: UNKNOWN
Platform: UNKNOWN
Requires-Dist: pybind11 (>=2.4)
